{
    "codeToName": {
        "0": "NULL",
        "29": ".notdef",
        "32": "space",
        "33": "exclam",
        "34": "quotedbl",
        "35": "numbersign",
        "36": "dollar",
        "37": "percent",
        "38": "ampersand",
        "39": "quotesingle",
        "40": "parenleft",
        "41": "parenright",
        "42": "asterisk",
        "43": "plus",
        "44": "comma",
        "45": "hyphen",
        "46": "period",
        "47": "slash",
        "48": "zero",
        "49": "one",
        "50": "two",
        "51": "three",
        "52": "four",
        "53": "five",
        "54": "six",
        "55": "seven",
        "56": "eight",
        "57": "nine",
        "58": "colon",
        "59": "semicolon",
        "60": "less",
        "61": "equal",
        "62": "greater",
        "63": "question",
        "64": "at",
        "65": "A",
        "66": "B",
        "67": "C",
        "68": "D",
        "69": "E",
        "70": "F",
        "71": "G",
        "72": "H",
        "73": "I",
        "74": "J",
        "75": "K",
        "76": "L",
        "77": "M",
        "78": "N",
        "79": "O",
        "80": "P",
        "81": "Q",
        "82": "R",
        "83": "S",
        "84": "T",
        "85": "U",
        "86": "V",
        "87": "W",
        "88": "X",
        "89": "Y",
        "90": "Z",
        "91": "bracketleft",
        "92": "backslash",
        "93": "bracketright",
        "94": "asciicircum",
        "95": "underscore",
        "96": "grave",
        "97": "a",
        "98": "b",
        "99": "c",
        "100": "d",
        "101": "e",
        "102": "f",
        "103": "g",
        "104": "h",
        "105": "i",
        "106": "j",
        "107": "k",
        "108": "l",
        "109": "m",
        "110": "n",
        "111": "o",
        "112": "p",
        "113": "q",
        "114": "r",
        "115": "s",
        "116": "t",
        "117": "u",
        "118": "v",
        "119": "w",
        "120": "x",
        "121": "y",
        "122": "z",
        "123": "braceleft",
        "124": "bar",
        "125": "braceright",
        "126": "asciitilde",
        "160": "space",
        "161": "exclamdown",
        "162": "cent",
        "163": "sterling",
        "164": "currency",
        "165": "yen",
        "166": "brokenbar",
        "167": "section",
        "168": "dieresis",
        "169": "copyright",
        "170": "ordfeminine",
        "171": "guillemotleft",
        "172": "logicalnot",
        "173": "softhyphen",
        "174": "registered",
        "175": "macron",
        "176": "degree",
        "177": "plusminus",
        "178": "twosuperior",
        "179": "threesuperior",
        "180": "acute",
        "181": "mu",
        "182": "paragraph",
        "183": "periodcentered",
        "184": "cedilla",
        "185": "onesuperior",
        "186": "ordmasculine",
        "187": "guillemotright",
        "188": "onequarter",
        "189": "onehalf",
        "190": "threequarters",
        "191": "questiondown",
        "198": "AE",
        "215": "multiply",
        "216": "Oslash",
        "222": "Thorn",
        "223": "germandbls",
        "230": "ae",
        "240": "eth",
        "247": "divide",
        "710": "circumflex",
        "711": "caron",
        "713": "uni02C9",
        "715": "uni02CB",
        "728": "breve",
        "729": "dotaccent",
        "730": "ring",
        "731": "ogonek",
        "732": "tilde",
        "733": "hungarumlaut",
        "755": "uni02F3",
        "768": "gravecomb",
        "769": "acutecomb",
        "771": "tildecomb",
        "777": "hookabovecomb",
        "783": "uni030F",
        "803": "dotbelowcomb",
        "1548": "uni060C",
        "1557": "uni0615",
        "1563": "uni061B",
        "1567": "uni061F",
        "1569": "uni0621",
        "1570": "uni0622",
        "1571": "uni0623",
        "1572": "uni0624",
        "1573": "uni0625",
        "1574": "uni0626",
        "1575": "uni0627",
        "1576": "uni0628",
        "1577": "uni0629",
        "1578": "uni062A",
        "1579": "uni062B",
        "1580": "uni062C",
        "1581": "uni062D",
        "1582": "uni062E",
        "1583": "uni062F",
        "1584": "uni0630",
        "1585": "uni0631",
        "1586": "uni0632",
        "1587": "uni0633",
        "1588": "uni0634",
        "1589": "uni0635",
        "1590": "uni0636",
        "1591": "uni0637",
        "1592": "uni0638",
        "1593": "uni0639",
        "1594": "uni063A",
        "1600": "uni0640",
        "1601": "uni0641",
        "1602": "uni0642",
        "1603": "uni0643",
        "1604": "uni0644",
        "1605": "uni0645",
        "1606": "uni0646",
        "1607": "uni0647",
        "1608": "uni0648",
        "1609": "uni0649",
        "1610": "uni064A",
        "1611": "uni064B",
        "1612": "uni064C",
        "1613": "uni064D",
        "1614": "uni064E",
        "1615": "uni064F",
        "1616": "uni0650",
        "1617": "uni0651",
        "1618": "uni0652",
        "1619": "uni0653",
        "1620": "uni0654",
        "1621": "uni0655",
        "1622": "uni0656",
        "1632": "uni0660",
        "1633": "uni0661",
        "1634": "uni0662",
        "1635": "uni0663",
        "1636": "uni0664",
        "1637": "uni0665",
        "1638": "uni0666",
        "1639": "uni0667",
        "1640": "uni0668",
        "1641": "uni0669",
        "1642": "uni066A",
        "1643": "uni066B",
        "1644": "uni066C",
        "1645": "uni066D",
        "1646": "uni066E",
        "1647": "uni066F",
        "1648": "uni0670",
        "1649": "uni0671",
        "1662": "uni067E",
        "1670": "uni0686",
        "1688": "uni0698",
        "1705": "uni06A9",
        "1711": "uni06AF",
        "1722": "uni06BA",
        "1728": "uni06C0",
        "1729": "uni06C1",
        "1730": "uni06C2",
        "1731": "uni06C3",
        "1740": "uni06CC",
        "1746": "uni06D2",
        "1747": "uni06D3",
        "1749": "uni06D5",
        "1776": "uni06F0",
        "1777": "uni06F1",
        "1778": "uni06F2",
        "1779": "uni06F3",
        "1780": "uni06F4",
        "1781": "uni06F5",
        "1782": "uni06F6",
        "1783": "uni06F7",
        "1784": "uni06F8",
        "1785": "uni06F9",
        "8192": "uni2000",
        "8193": "uni2001",
        "8194": "uni2002",
        "8195": "uni2003",
        "8196": "uni2004",
        "8197": "uni2005",
        "8198": "uni2006",
        "8199": "uni2007",
        "8200": "uni2008",
        "8201": "uni2009",
        "8202": "uni200A",
        "8203": "ZWSP",
        "8204": "uni200C",
        "8205": "uni200D",
        "8206": "uni200E",
        "8207": "uni200F",
        "8208": "uni2010",
        "8209": "uni2011",
        "8211": "endash",
        "8212": "emdash",
        "8213": "horizontalbar",
        "8215": "underscoredbl",
        "8216": "quoteleft",
        "8217": "quoteright",
        "8218": "quotesinglbase",
        "8219": "quotereversed",
        "8220": "quotedblleft",
        "8221": "quotedblright",
        "8222": "quotedblbase",
        "8224": "dagger",
        "8225": "daggerdbl",
        "8226": "bullet",
        "8229": "twodotenleader",
        "8230": "ellipsis",
        "8231": "uni2027",
        "8240": "perthousand",
        "8242": "minute",
        "8243": "second",
        "8249": "guilsinglleft",
        "8250": "guilsinglright",
        "8252": "exclamdbl",
        "8260": "fraction",
        "8706": "partialdiff",
        "8710": "increment",
        "8719": "product",
        "8721": "summation",
        "8722": "minus",
        "8730": "radical",
        "8734": "infinity",
        "8747": "integral",
        "8776": "approxequal",
        "8800": "notequal",
        "8804": "lessequal",
        "8805": "greaterequal",
        "64336": "uni0671",
        "64337": "uni0671.fina",
        "64342": "uni067E",
        "64343": "uni067E.fina",
        "64344": "uni067E.init",
        "64345": "uni067E.medi",
        "64378": "uni0686",
        "64379": "uni0686.fina",
        "64380": "uni0686.init",
        "64381": "uni0686.medi",
        "64394": "uni0698",
        "64395": "uni0698.fina",
        "64398": "uni06A9",
        "64399": "uni06A9.fina",
        "64400": "uni06A9.init",
        "64401": "uni06A9.medi",
        "64402": "uni06AF",
        "64403": "uni06AF.fina",
        "64404": "uni06AF.init",
        "64405": "uni06AF.medi",
        "64414": "uni06BA",
        "64415": "uni06BA.fina",
        "64420": "uni06C0",
        "64421": "uni06C0.fina",
        "64422": "uni06C1",
        "64423": "uni06C1.fina",
        "64428": "uni06BE.init",
        "64429": "uni06BE.medi",
        "64430": "uni06D2",
        "64431": "uni06D2.fina",
        "64432": "uni06D3",
        "64433": "uni06D3.fina",
        "64488": "uni0649.init",
        "64489": "uni0649.medi",
        "64508": "uni06CC",
        "64509": "uni06CC.fina",
        "64510": "uni06CC.init",
        "64511": "uni06CC.medi",
        "64606": "uni0651064C",
        "64607": "uni0651064D",
        "64608": "uni0651064E",
        "64609": "uni0651064F",
        "64610": "uni06510650",
        "64611": "uniFC63",
        "64830": "uniFD3E",
        "64831": "uniFD3F",
        "65010": "allah",
        "65020": "riyal",
        "65136": "fathatan_01",
        "65138": "dammatan_01",
        "65140": "kasratan_01",
        "65142": "fatha_01",
        "65144": "damma_01",
        "65146": "kasra_01",
        "65148": "shadda_01",
        "65150": "sukun_01",
        "65152": "uni0621",
        "65153": "uni0622",
        "65154": "uni0622.fina",
        "65155": "uni0623",
        "65156": "uni0623.fina",
        "65157": "uni0624",
        "65158": "uni0624.fina",
        "65159": "uni0625",
        "65160": "uni0625.fina",
        "65161": "uni0626",
        "65162": "uni0626.fina",
        "65163": "uni0626.init",
        "65164": "uni0626.medi",
        "65165": "uni0627",
        "65166": "uni0627.fina",
        "65167": "uni0628",
        "65168": "uni0628.fina",
        "65169": "uni0628.init",
        "65170": "uni0628.medi",
        "65171": "uni0629",
        "65172": "uni0629.fina",
        "65173": "uni062A",
        "65174": "uni062A.fina",
        "65175": "uni062A.init",
        "65176": "uni062A.medi",
        "65177": "uni062B",
        "65178": "uni062B.fina",
        "65179": "uni062B.init",
        "65180": "uni062B.medi",
        "65181": "uni062C",
        "65182": "uni062C.fina",
        "65183": "uni062C.init",
        "65184": "uni062C.medi",
        "65185": "uni062D",
        "65186": "uni062D.fina",
        "65187": "uni062D.init",
        "65188": "uni062D.medi",
        "65189": "uni062E",
        "65190": "uni062E.fina",
        "65191": "uni062E.init",
        "65192": "uni062E.medi",
        "65193": "uni062F",
        "65194": "uni062F.fina",
        "65195": "uni0630",
        "65196": "uni0630.fina",
        "65197": "uni0631",
        "65198": "uni0631.fina",
        "65199": "uni0632",
        "65200": "uni0632.fina",
        "65201": "uni0633",
        "65202": "uni0633.fina",
        "65203": "uni0633.init",
        "65204": "uni0633.medi",
        "65205": "uni0634",
        "65206": "uni0634.fina",
        "65207": "uni0634.init",
        "65208": "uni0634.medi",
        "65209": "uni0635",
        "65210": "uni0635.fina",
        "65211": "uni0635.init",
        "65212": "uni0635.medi",
        "65213": "uni0636",
        "65214": "uni0636.fina",
        "65215": "uni0636.init",
        "65216": "uni0636.medi",
        "65217": "uni0637",
        "65218": "uni0637.fina",
        "65219": "uni0637.init",
        "65220": "uni0637.medi",
        "65221": "uni0638",
        "65222": "uni0638.fina",
        "65223": "uni0638.init",
        "65224": "uni0638.medi",
        "65225": "uni0639",
        "65226": "uni0639.fina",
        "65227": "uni0639.init",
        "65228": "uni0639.medi",
        "65229": "uni063A",
        "65230": "uni063A.fina",
        "65231": "uni063A.init",
        "65232": "uni063A.medi",
        "65233": "uni0641",
        "65234": "uni0641.fina",
        "65235": "uni0641.init",
        "65236": "uni0641.medi",
        "65237": "uni0642",
        "65238": "uni0642.fina",
        "65239": "uni0642.init",
        "65240": "uni0642.medi",
        "65241": "uni0643",
        "65242": "uni0643.fina",
        "65243": "uni0643.init",
        "65244": "uni0643.medi",
        "65245": "uni0644",
        "65246": "uni0644.fina",
        "65247": "uni0644.init",
        "65248": "uni0644.medi",
        "65249": "uni0645",
        "65250": "uni0645.fina",
        "65251": "uni0645.init",
        "65252": "uni0645.medi",
        "65253": "uni0646",
        "65254": "uni0646.fina",
        "65255": "uni0646.init",
        "65256": "uni0646.medi",
        "65257": "uni0647",
        "65258": "uni0647.fina",
        "65259": "uni0647.init",
        "65260": "uni0647.medi",
        "65261": "uni0648",
        "65262": "uni0648.fina",
        "65263": "uni0649",
        "65264": "uni0649.fina",
        "65265": "uni064A",
        "65266": "uni064A.fina",
        "65267": "uni064A.init",
        "65268": "uni064A.medi",
        "65269": "uni06440622.isol",
        "65270": "uni06440622.fina",
        "65271": "uni06440623.isol",
        "65272": "uni06440623.fina",
        "65273": "uni06440625.isol",
        "65274": "uni06440625.fina",
        "65275": "uni06440627.isol",
        "65276": "uni06440627.fina",
        "65279": "NULL"
    },
    "isUnicode": true,
    "EncodingScheme": "FontSpecific",
    "FontName": "IRANSansDN",
    "FullName": "IRANSansDN",
    "Version": "Version 1.00 December 14, 2017, initial release",
    "PostScriptName": "IRANSansDN",
    "Weight": "Medium",
    "ItalicAngle": "0",
    "IsFixedPitch": "false",
    "UnderlineThickness": "43",
    "UnderlinePosition": "-261",
    "FontHeightOffset": "0",
    "Ascender": "1043",
    "Descender": "-522",
    "FontBBox": [
        "-481",
        "-518",
        "1376",
        "1189"
    ],
    "StartCharMetrics": "472",
    "C": {
        "0": 0,
        "29": 534,
        "32": 303,
        "33": 252,
        "34": 320,
        "35": 616,
        "36": 562,
        "37": 733,
        "38": 622,
        "39": 174,
        "40": 356,
        "41": 345,
        "42": 431,
        "43": 567,
        "44": 196,
        "45": 276,
        "46": 283,
        "47": 412,
        "48": 562,
        "49": 562,
        "50": 562,
        "51": 562,
        "52": 562,
        "53": 562,
        "54": 562,
        "55": 562,
        "56": 562,
        "57": 562,
        "58": 261,
        "59": 211,
        "60": 508,
        "61": 549,
        "62": 523,
        "63": 472,
        "64": 898,
        "65": 652,
        "66": 623,
        "67": 651,
        "68": 656,
        "69": 568,
        "70": 553,
        "71": 681,
        "72": 713,
        "73": 272,
        "74": 552,
        "75": 627,
        "76": 538,
        "77": 873,
        "78": 713,
        "79": 687,
        "80": 631,
        "81": 687,
        "82": 616,
        "83": 593,
        "84": 597,
        "85": 648,
        "86": 636,
        "87": 887,
        "88": 627,
        "89": 600,
        "90": 599,
        "91": 265,
        "92": 410,
        "93": 265,
        "94": 418,
        "95": 451,
        "96": 309,
        "97": 544,
        "98": 561,
        "99": 523,
        "100": 564,
        "101": 530,
        "102": 347,
        "103": 561,
        "104": 551,
        "105": 243,
        "106": 239,
        "107": 507,
        "108": 243,
        "109": 877,
        "110": 552,
        "111": 570,
        "112": 561,
        "113": 568,
        "114": 338,
        "115": 516,
        "116": 327,
        "117": 551,
        "118": 484,
        "119": 751,
        "120": 496,
        "121": 473,
        "122": 496,
        "123": 338,
        "124": 243,
        "125": 338,
        "126": 680,
        "160": 303,
        "161": 243,
        "162": 547,
        "163": 581,
        "164": 713,
        "165": 606,
        "166": 240,
        "167": 613,
        "168": 418,
        "169": 786,
        "170": 447,
        "171": 469,
        "172": 554,
        "173": 276,
        "174": 786,
        "175": 458,
        "176": 373,
        "177": 534,
        "178": 367,
        "179": 367,
        "180": 313,
        "181": 567,
        "182": 489,
        "183": 261,
        "184": 247,
        "185": 367,
        "186": 455,
        "187": 469,
        "188": 733,
        "189": 776,
        "190": 778,
        "191": 473,
        "198": 935,
        "215": 533,
        "216": 687,
        "222": 591,
        "223": 595,
        "230": 844,
        "240": 586,
        "247": 571,
        "710": 471,
        "711": 444,
        "713": 459,
        "715": 200,
        "728": 427,
        "729": 243,
        "730": 334,
        "731": 270,
        "732": 472,
        "733": 373,
        "755": 294,
        "768": 0,
        "769": 0,
        "771": 0,
        "777": 0,
        "783": 0,
        "803": 242,
        "1548": 274,
        "1557": 0,
        "1563": 223,
        "1567": 445,
        "1569": 443,
        "1570": 432,
        "1571": 236,
        "1572": 464,
        "1573": 221,
        "1574": 772,
        "1575": 233,
        "1576": 875,
        "1577": 430,
        "1578": 875,
        "1579": 875,
        "1580": 716,
        "1581": 716,
        "1582": 716,
        "1583": 490,
        "1584": 490,
        "1585": 401,
        "1586": 401,
        "1587": 1170,
        "1588": 1170,
        "1589": 1268,
        "1590": 1268,
        "1591": 790,
        "1592": 790,
        "1593": 666,
        "1594": 666,
        "1600": 394,
        "1601": 862,
        "1602": 687,
        "1603": 880,
        "1604": 645,
        "1605": 538,
        "1606": 697,
        "1607": 430,
        "1608": 469,
        "1609": 780,
        "1610": 780,
        "1611": 0,
        "1612": 0,
        "1613": 0,
        "1614": 0,
        "1615": 0,
        "1616": 0,
        "1617": 0,
        "1618": 0,
        "1619": 0,
        "1620": 0,
        "1621": 0,
        "1622": 0,
        "1632": 430,
        "1633": 288,
        "1634": 494,
        "1635": 626,
        "1636": 480,
        "1637": 539,
        "1638": 507,
        "1639": 561,
        "1640": 587,
        "1641": 477,
        "1642": 529,
        "1643": 300,
        "1644": 222,
        "1645": 490,
        "1646": 875,
        "1647": 687,
        "1648": 0,
        "1649": 309,
        "1662": 875,
        "1670": 716,
        "1688": 449,
        "1705": 1009,
        "1711": 1009,
        "1722": 697,
        "1728": 432,
        "1729": 427,
        "1730": 432,
        "1731": 427,
        "1740": 780,
        "1746": 734,
        "1747": 734,
        "1749": 430,
        "1776": 430,
        "1777": 288,
        "1778": 494,
        "1779": 626,
        "1780": 547,
        "1781": 600,
        "1782": 511,
        "1783": 561,
        "1784": 587,
        "1785": 477,
        "8192": 510,
        "8193": 1020,
        "8194": 510,
        "8195": 1020,
        "8196": 340,
        "8197": 255,
        "8198": 170,
        "8199": 562,
        "8200": 273,
        "8201": 204,
        "8202": 102,
        "8203": 0,
        "8204": 0,
        "8205": 0,
        "8206": 0,
        "8207": 0,
        "8208": 275,
        "8209": 275,
        "8211": 656,
        "8212": 781,
        "8213": 781,
        "8215": 456,
        "8216": 200,
        "8217": 200,
        "8218": 199,
        "8219": 200,
        "8220": 353,
        "8221": 357,
        "8222": 344,
        "8224": 551,
        "8225": 570,
        "8226": 337,
        "8229": 471,
        "8230": 669,
        "8231": 120,
        "8240": 958,
        "8242": 174,
        "8243": 320,
        "8249": 300,
        "8250": 300,
        "8252": 515,
        "8260": 455,
        "8706": 570,
        "8710": 705,
        "8719": 694,
        "8721": 586,
        "8722": 571,
        "8730": 596,
        "8734": 1028,
        "8747": 256,
        "8776": 563,
        "8800": 549,
        "8804": 508,
        "8805": 523,
        "64336": 309,
        "64337": 293,
        "64342": 875,
        "64343": 1007,
        "64344": 367,
        "64345": 370,
        "64378": 716,
        "64379": 740,
        "64380": 704,
        "64381": 740,
        "64394": 449,
        "64395": 428,
        "64398": 1009,
        "64399": 989,
        "64400": 499,
        "64401": 520,
        "64402": 1009,
        "64403": 989,
        "64404": 499,
        "64405": 520,
        "64414": 697,
        "64415": 751,
        "64420": 432,
        "64421": 503,
        "64422": 427,
        "64423": 586,
        "64428": 662,
        "64429": 459,
        "64430": 734,
        "64431": 539,
        "64432": 734,
        "64433": 539,
        "64488": 314,
        "64489": 325,
        "64508": 780,
        "64509": 746,
        "64510": 367,
        "64511": 370,
        "64606": 0,
        "64607": 0,
        "64608": 0,
        "64609": 0,
        "64610": 0,
        "64611": 0,
        "64830": 404,
        "64831": 380,
        "65010": 892,
        "65020": 1412,
        "65136": 0,
        "65138": 0,
        "65140": 0,
        "65142": 0,
        "65144": 0,
        "65146": 0,
        "65148": 0,
        "65150": 0,
        "65152": 443,
        "65153": 432,
        "65154": 326,
        "65155": 236,
        "65156": 278,
        "65157": 464,
        "65158": 453,
        "65159": 221,
        "65160": 278,
        "65161": 772,
        "65162": 746,
        "65163": 364,
        "65164": 370,
        "65165": 233,
        "65166": 271,
        "65167": 875,
        "65168": 1007,
        "65169": 311,
        "65170": 325,
        "65171": 430,
        "65172": 503,
        "65173": 875,
        "65174": 1007,
        "65175": 367,
        "65176": 370,
        "65177": 875,
        "65178": 1007,
        "65179": 367,
        "65180": 370,
        "65181": 716,
        "65182": 740,
        "65183": 704,
        "65184": 740,
        "65185": 716,
        "65186": 740,
        "65187": 704,
        "65188": 740,
        "65189": 716,
        "65190": 740,
        "65191": 704,
        "65192": 740,
        "65193": 490,
        "65194": 549,
        "65195": 490,
        "65196": 549,
        "65197": 401,
        "65198": 432,
        "65199": 401,
        "65200": 432,
        "65201": 1170,
        "65202": 1256,
        "65203": 721,
        "65204": 821,
        "65205": 1170,
        "65206": 1256,
        "65207": 721,
        "65208": 821,
        "65209": 1268,
        "65210": 1247,
        "65211": 835,
        "65212": 853,
        "65213": 1268,
        "65214": 1247,
        "65215": 835,
        "65216": 853,
        "65217": 790,
        "65218": 812,
        "65219": 685,
        "65220": 688,
        "65221": 790,
        "65222": 812,
        "65223": 685,
        "65224": 688,
        "65225": 666,
        "65226": 590,
        "65227": 495,
        "65228": 508,
        "65229": 666,
        "65230": 590,
        "65231": 495,
        "65232": 508,
        "65233": 862,
        "65234": 916,
        "65235": 405,
        "65236": 435,
        "65237": 687,
        "65238": 683,
        "65239": 405,
        "65240": 435,
        "65241": 880,
        "65242": 903,
        "65243": 499,
        "65244": 520,
        "65245": 645,
        "65246": 666,
        "65247": 247,
        "65248": 293,
        "65249": 538,
        "65250": 554,
        "65251": 507,
        "65252": 528,
        "65253": 697,
        "65254": 751,
        "65255": 311,
        "65256": 325,
        "65257": 430,
        "65258": 503,
        "65259": 662,
        "65260": 459,
        "65261": 469,
        "65262": 453,
        "65263": 780,
        "65264": 746,
        "65265": 780,
        "65266": 746,
        "65267": 364,
        "65268": 370,
        "65269": 597,
        "65270": 643,
        "65271": 552,
        "65272": 608,
        "65273": 552,
        "65274": 608,
        "65275": 550,
        "65276": 608,
        "65279": 0
    },
    "CIDtoGID_Compressed": true,
    "CIDtoGID": "eJzt1lWMVWcUhuHvS5GiLe7u7jVquLu7O9SACu7u7u7u7u4utYuGpu6eykV36IQcmJkwwwSGpO+TrP3bOmuv\/5ybIytmnnAyp3Yap3U6p3cGJ3cKZ3QmZ3YWp3RWZ3N253BO53Ju53Fe53N+p3IBF3QhF3YRF3UxF3cJl3QpP+Nn\/Zyf9wsu7Rf9kl\/2K37VZVzW5VzeFVzRlVzZVVzV1VzdNVzTtVzbdVzX9VzfDdzQjdzYTdzUzdzcLdzSrdzabdzW7dzeHdzRndzZXdzV3dzdPfxaDO\/+3\/1ne47nep7ne4EXepFf92K\/4SVe6je9zMu9wiu9yqu9xmu9zuu9wRv9ljd5s7d4a2gpb7vfy9zT20NWO7zzrtNdEXxi912rXtG7HIBHxXu8N3juC2J\/pDkHfNCHfNhHfDQalY9FejLN04Pn1JCdGSHzmVGsPyvqvQAAHmtNw+10D5k3CxubBBFHA9RHx9VPVxVXQzRFYzRBMxRfc5RIC5RYi5RUy5Rcq5Ra65Rem0IqldQO7VNWZVduHVJ+FVZRnVUrtVNrtVFbtVcHdVQndVYXdYugzzIqq3IqrwqqqEqqrCqqqsZqrhZqqVIqra4aFOkdR9yzjsq\/4yX3zagdMq8bYUbDkPlR3dIn+jRczvmQeU1dDp5HotBdeF\/oS32lr1VN1VVD3+o7ffNAdQAAAAAAAAAAAAAAAAAAAAAAABAr3Ntv+x2\/6\/fcx33dz\/09wAOdwAmdyImdxIM8OMga4qE+HownPMzDPcIjPcqjPSbYOelTHn+70gRP9Olw9c8EMcmTQ3bGelzwPHtP3pSHe08AEfO5sPF8uJMLQVz0pXt2L4eNVyKtePWBe7kWzfzrYeMN33zQdwIAAAAAAAAAAAAAAAAAAAAAAAAAAAAAAAAAAAAAAAAAAAAAAAAAAAAAAAAAAAAAAAAAAAAAAAAAAAAAAAAAAAAAAAAAAAAAAAAAAAAAAAAAAAAAAAAAAAAAAAAAAAAAAAAAAAAAAAAAAAAAAAAAAAAAAAAAAAAAAAAAAAAAAAAAAAAAAAAAAAAAAAAAAAAAAAAAAAAAAAAAAAAAAAAAAAAAEGODNPjOfIRGapRGx7hmL\/XWNE2P9HyJlt4ea6uOtmm76qqB6ql+uLyGanRnflTHdEs976w\/0+eqqVq6rCsx7jc6TupUlPLO65Iu6OJD7ubh+l1\/6E\/9pb\/1T2y3guhzPMeP7R7+Dxwngr24j76PWPF9ED8E8WMQPwXxcxC\/BPFrEL8FEUcDNFB91FfHdUL91F9XdUPXdF1xFU9DNFxDNUxTNFVjNF5jNU4TNFkTNUkzNFszNUvxlVBPKoHmaL7map4SqYcWaKESK4kWabGSKpme0tNappVarhVKrlRKoZRapbVarTVKrXRKo7Rap41arw1Kr0zKoIzapK3arC3aod3aqV3ap\/3ao73KqmzKrCzKrlzKoZzKrXzKo7w6pMM6oIPKr0IqoIIqrCIqqmI6q3M6rTP6SB\/rpt7XB\/pQxVXi9rfj2PlR8Lj4F1IU4XY=",
    "_version_": 6
}